{
  "name": "Don Craig",
  "age": 18,
  "address": {
    "street": "Wugre Boulevard",
    "city": "Jozudcew",
    "state": "IL",
    "zip": "82106"
  },
  "contact": {
    "phone": "(969) 326-6706",
    "servicePhone": "800758381"
  },
  "birthday": "1984-03-16T00:12:19.007Z",
  "ip": "187.252.113.171",
  "foo": "bar",
  "profile": {
    "about": "Tefimdu mecizu pug aki on ridareh ak fiwirjuh adowaczu gafuwo sevneag nenurofe esmejle. Vohikra ebgimgo rida fi vojasuc hav movuud cozjif sejsikuw egewewtan razu bire lalnottor nihozol ponel. Lanfev socgoc so pe lat pomapum nu dulcefam ku are vufuc gihici we owa bihiljo. Rusjo ocikoco be bu wodfewab zif tem tube reitfuk if keoriicu ni ab cipfe sefmaw foefu lan copamaohi. Ze cibrusbiw jovimbol bowepunim tu vawor pete ba tu ihuruc ac edgogfuf elobowmow. Focak wobdowa gewfepov wucenih sajit supejazan momguw ecu ebuceh urosec nizleda itsun bavafop de jujot. Ok boguf gasagep gase zisaje epjuf hene rorza puspujvu zopzacno saope luhihtiv guujo.",
    "bio": "Om wacujgej vulaido dab ajoariuh uk huwafu dufer nejog gajdewwir dogazeka natdun uporar. Ma lelha imji udutiwo giussan si ucahu alzuj obajus lubibcac jawug ra ik bo pukepeor. Leb owi moswinag weruvij zihisuc vavo pizujez puv ca na pod ra cewom hawu. Fuhse wero edsoc duwso jaabpak sej ko za morefite bec fopur rile ok duvogfiv fi bitic be. Ziccatu ivhol towovit casuvumi ijwa onilut mobigu bo watazzi lubaw rebo jamnavri datto. Bori ojoel fevbavko tekrebje zalgusu kep ko hojli wi permaom og ja om."
  },
  "apiKey": "46ce1d9d72dd676712b1f0effbb87ba294c13a615ec34fc5ea3bd2e6fb61f96a",
  "currency": {
    "code": "XDR",
    "name": "International Monetary Fund (IMF) Special Drawing Rights"
  }
}