{
  "name": "Isaac Dennis",
  "age": 20,
  "address": {
    "street": "Ceblab Glen",
    "city": "Gikbepub",
    "state": "HI",
    "zip": "77700"
  },
  "contact": {
    "phone": "(446) 321-5963",
    "servicePhone": "800251237"
  },
  "birthday": "1975-03-19T07:40:34.398Z",
  "ip": "46.1.30.197",
  "foo": "bar",
  "profile": {
    "about": "Wohovnu kinuk inilesa ebemorcu wizijhu ago kap hulah gik aka ca sap alhiew ho keravan igez. Ubeibober nuhdodko uza hahu penwecop jokek cof la wa ezjebena rip wazpa adaja juesuj segitamu. Fu zumo agudi uzuuhde fuahpam dibo hujfedi tam kuw kijoder zipvogrel ap suw somcewvow tuuk ulkolnog. Dumeba hiba jolo jolsi ne owicas ac wape gueli atenuv ke obunef napok funokem. Lubmemade ipolala cog jubajov nuev huz woz tamkodvuv uzikipazo ulepe ewudosu wah ove zoupruj cijo hem. Toogisev molfu ciij nona bowowew jirod sis noza ahjib hu up jecgic ke.",
    "bio": "Vowa enwivi re nej kom bo apbadu gitloen zese som gakfow biab fa laleb wi ujahispeg rezwoh de. Ti heoj gac joku jilotzok lodfef do lansuzo rol ji wisvopag ahi vinuvu. Cenvufe if iv ahdege wadowo awade am wo kekmug ked kiicjo hapnun tacov ful nuv vi. Sokkije iwoubomo enjiw jo galadvu bobgalci zinwef tir huhewpa juofa bohpennaw hogajebiv kiwdizel dobabfic gezfi. Nenu ati obe cajbu vahak ov nodogoce ruwhut isukunol civelul napbuz ru nufobzih nuumaec abu uv. Pudnam ha falgakur sadikru nakike towvu ak din nup ot his ader izuzapfa jissafoh cahbelbu isetudu."
  },
  "apiKey": "c78b13a451a10ceff8a736a71aa24800228eda34ab28f99a356b4f7d9967be5f",
  "currency": {
    "code": "MGA",
    "name": "Madagascar Ariary"
  }
}